transaction_analyzer/__init__.py
transaction_analyzer/analyzer.py
yet_another_shtransaction_analyzer-0.1.0.dist-info/METADATA
yet_another_shtransaction_analyzer-0.1.0.dist-info/WHEEL
yet_another_shtransaction_analyzer-0.1.0.dist-info/entry_points.txt
yet_another_shtransaction_analyzer-0.1.0.dist-info/top_level.txt
yet_another_shtransaction_analyzer-0.1.0.dist-info/RECORD
