Metadata-Version: 2.1
Name: yet_another_shtransaction_analyzer
Version: 0.1.0
Author-email: Your Name <your.email@example.com>
Requires-Dist: pandas
